[{"id":"https://w3id.org/dsh/schulfaecher/","title":{"de":"Schulfächer an einer deutschen Schule in Finnland","fi":"Kouluaineet saksalaisessa koulussa suomessa"},"dc_title":null,"prefLabel":null,"description":null,"dc_description":null,"languages":["de","fi"]},{"id":"http://example.org/trinken-vokabular#Trinken_Vokabular","title":{"de":"Konzeptvokabular zum semantischen Feld Trinken","fi":null},"dc_title":null,"prefLabel":{"de":"Trinken-Vokabular","fi":null},"description":{"de":null,"fi":null},"dc_description":null,"languages":["de"]}]