[{"blue":["https://acka47.github.io/skohub-pages/colour/blue"],"blu":["https://acka47.github.io/skohub-pages/colour/blue"],"bl":["https://acka47.github.io/skohub-pages/colour/blue"],"b":["https://acka47.github.io/skohub-pages/colour/blue"],"lue":["https://acka47.github.io/skohub-pages/colour/blue"],"lu":["https://acka47.github.io/skohub-pages/colour/blue"],"l":["https://acka47.github.io/skohub-pages/colour/blue","https://acka47.github.io/skohub-pages/colour/violet"],"ue":["https://acka47.github.io/skohub-pages/colour/blue"],"u":["https://acka47.github.io/skohub-pages/colour/blue"],"e":["https://acka47.github.io/skohub-pages/colour/blue","https://acka47.github.io/skohub-pages/colour/violet"],"violet":["https://acka47.github.io/skohub-pages/colour/violet"],"viole":["https://acka47.github.io/skohub-pages/colour/violet"],"viol":["https://acka47.github.io/skohub-pages/colour/violet"],"vio":["https://acka47.github.io/skohub-pages/colour/violet"],"vi":["https://acka47.github.io/skohub-pages/colour/violet"],"v":["https://acka47.github.io/skohub-pages/colour/violet"],"iolet":["https://acka47.github.io/skohub-pages/colour/violet"],"iole":["https://acka47.github.io/skohub-pages/colour/violet"],"iol":["https://acka47.github.io/skohub-pages/colour/violet"],"io":["https://acka47.github.io/skohub-pages/colour/violet"],"i":["https://acka47.github.io/skohub-pages/colour/violet"],"olet":["https://acka47.github.io/skohub-pages/colour/violet"],"ole":["https://acka47.github.io/skohub-pages/colour/violet"],"ol":["https://acka47.github.io/skohub-pages/colour/violet"],"o":["https://acka47.github.io/skohub-pages/colour/violet"],"let":["https://acka47.github.io/skohub-pages/colour/violet"],"le":["https://acka47.github.io/skohub-pages/colour/violet"],"et":["https://acka47.github.io/skohub-pages/colour/violet"],"t":["https://acka47.github.io/skohub-pages/colour/violet"]},{},{},{},{},{},{},{},{}]